[
  {
    "province": "Groningen (PV)",
    "percentage": "14,2"
  },
  {
    "province": "Friesland (PV)",
    "percentage": "12,0"
  },
  {
    "province": "Drenthe (PV)",
    "percentage": "16,5"
  },
  {
    "province": "Overijssel (PV)",
    "percentage": "15,5"
  },
  {
    "province": "Flevoland (PV)",
    "percentage": "14,1"
  },
  {
    "province": "Gelderland (PV)",
    "percentage": "14,4"
  },
  {
    "province": "Utrecht (PV)",
    "percentage": "12,1"
  },
  {
    "province": "Noord-Holland (PV)",
    "percentage": "13,4"
  },
  {
    "province": "Zuid-Holland (PV)",
    "percentage": "15,9"
  },
  {
    "province": "Zeeland (PV)",
    "percentage": "16,0"
  },
  {
    "province": "Noord-Brabant (PV)",
    "percentage": "15,9"
  },
  {
    "province": "Limburg (PV)",
    "percentage": "16,3"
  }
]